{"logo":"AutoMotive",
  "home": "Home",
  "login":"Login",
  "signUp": "Sign Up",
  "account": "Create Account",
  "welcome": "Welcome Back",
  "enterPass": "Enter Your Password",
  "passLength": "Please Enter Password Has 8 Chars or More",
  "validPass": "Please Enter a Valid Password",
  "forgetPass": "Forget Password?",
  "reEnterPass": "Re-enter New Password",
  "passNotMatch": "Passwords Don't Match",
  "reset": "Reset",
  "resetPass": "Reset Password",
  "enterUser":"Enter Your Name",
  "userLength":"Please Enter a Name Has 4 Chars or More",
  "enterMail":"Enter Your Email",
  "validMail": "Enter Valid Email",
  "sendMail": "We Have Sent You an Email",
  "notExist": "Email Not Exist",
  "faceLog":"Login with Face ID",
  "faceReg":"Register with Face ID",
  "faceId": "Face ID",
  "noAccount":"Don't Have Account?",
  "registered":"Already Registered?",
  "disabled": "User disabled",
  "notAllowed":"Server error, please try again later",
  "confirm":"Confirm",
  "logFailed": "Login Failed",
  "wrongUser": "Wrong User Name",
  "wrongPass": "Wrong Password",
  "temp":"Temperature",
  "perform":"Performance",
  "battery":"Battery",
  "charge": "Charging",
  "km": "km",
  "km/h": "km/h",
  "speed":"Speed",
  "consum":"Consumed Distance",
  "setting":"Settings",
  "noAcount": "This Account isn't Registered",
  "accountExist": "This Account is Already Registered",
  "failed": "Failed,Please Try Again",
  "lang":"Language",
  "chPass":"Change Password",
  "oPass":"Old Password",
  "nPass":"New Password",
  "updateFailed":"Update Failed",
  "updateSuccess": "Updated Successfully",
  "logout":"Logout",
  "mood":"Dark Mood",
  "control":"Controls",
  "getCar": "Get The Car",
  "enableBiometrics": "Enable Biometrics",
  "flash": "Flash",
  "klaxon": "Klaxon",
  "wait":"Wait",
  "cam":"Camera",
  "gps":"GPS",
  "parking":"Parking" ,
  "carParked": "The car is already parked"

}